{
  "menuName": "Русско-шведский разговорник / Russian-Swedish phrasebook",
  "description": "Russian-Swedish travel phrases",
  "langA": "Russian",
  "langB": "Swedish",
  "inputEqu": [
    {
      "key": [
        "е",
        "Е"
      ],
      "value": [
        "ё",
        "Ё"
      ]
    },
    {
      "key": [
        "ё",
        "Ё"
      ],
      "value": [
        "е",
        "Е"
      ]
    },
    {
      "key": [
        "a",
        "A"
      ],
      "value": [
        "å",
        "Å",
        "ä",
        "Ä"
      ]
    },
    {
      "key": [
        "o",
        "O"
      ],
      "value": [
        "ö",
        "Ö"
      ]
    }
  ],
  "lines": [
    {
      "A": "Да",
      "B": "ja"
    },
    {
      "A": "Нет",
      "B": "nej"
    },
    {
      "A": "Спасибо",
      "B": "tack"
    },
    {
      "A": "Пожалуйста",
      "B": "snälla"
    },
    {
      "A": "Извините",
      "B": "ledsen"
    },
    {
      "A": "Здравствуйте",
      "B": "hej"
    },
    {
      "A": "До свидания",
      "B": "hejdå"
    },
    {
      "A": "Пока",
      "B": "stund"
    },
    {
      "A": "Доброе утро",
      "B": "god morgon"
    },
    {
      "A": "Добрый вечер",
      "B": "god kväll"
    },
    {
      "A": "Спокойной ночи",
      "B": "god natt"
    },
    {
      "A": "Я не понимаю",
      "B": "jag förstår inte"
    },
    {
      "A": "Как вас зовут",
      "B": "vad är ditt namn"
    },
    {
      "A": "Очень приятно",
      "B": "nöje"
    },
    {
      "A": "Как дела",
      "B": "hur mår du"
    },
    {
      "A": "Хорошо",
      "B": "ok"
    },
    {
      "A": "Так себе",
      "B": "så så"
    },
    {
      "A": "Где здесь туалет",
      "B": "var finns toaletter"
    },
    {
      "A": "Сколько стоит билет?",
      "B": "hur mycket kostar biljetten?"
    },
    {
      "A": "Один билет до",
      "B": "en biljett till"
    },
    {
      "A": "Где вы живете?",
      "B": "var bor du?"
    },
    {
      "A": "Который час?",
      "B": "vad är klockan?"
    },
    {
      "A": "Не курить",
      "B": "rökning"
    },
    {
      "A": "ВХОД",
      "B": "INTRÄDE"
    },
    {
      "A": "ВЫХОД",
      "B": "ÅTERKALLANDE"
    },
    {
      "A": "Вход запрещен",
      "B": "inträde förbjudet"
    },
    {
      "A": "Вы говорите по-английски?",
      "B": "talar du engelska?"
    },
    {
      "A": "Где находится метро?",
      "B": "var är Tunnelbanan?"
    },
    {
      "A": "Один билет до центра города, пожалуйста",
      "B": "en biljett till centrum, tack"
    },
    {
      "A": "Хорошо, я покупаю это",
      "B": "tja, jag köper den"
    },
    {
      "A": "Что это такое?",
      "B": "vad är det?"
    },
    {
      "A": "Мне нужно заказать номер",
      "B": "jag behöver reserv"
    },
    {
      "A": "Я хочу заказать номер",
      "B": "jag vill reservera"
    },
    {
      "A": "Сколько стоит",
      "B": "hur mycket kostar det"
    },
    {
      "A": "Номер с ванной",
      "B": "rum med bad"
    },
    {
      "A": "Я заказывал у вас номер",
      "B": "jag beställde ditt rum"
    },
    {
      "A": "Примите заказ",
      "B": "acceptera för"
    },
    {
      "A": "Чаевые",
      "B": "tips"
    },
    {
      "A": "Я хочу оплатить счет",
      "B": "jag vill betala räkningen"
    },
    {
      "A": "Паспорт",
      "B": "pass"
    },
    {
      "A": "Комната",
      "B": "rum"
    },
    {
      "A": "Сколько стоит",
      "B": "hur mycket kostar det"
    },
    {
      "A": "Наличными",
      "B": "kontanter"
    },
    {
      "A": "Безналичными",
      "B": "för icke-kontanta"
    },
    {
      "A": "Чеком",
      "B": "check"
    },
    {
      "A": "Какой способ оплаты",
      "B": "vilka betalningssätt"
    },
    {
      "A": "Сигареты",
      "B": "cigaretter"
    },
    {
      "A": "Хлеб",
      "B": "bröd"
    },
    {
      "A": "Продукты",
      "B": "produkter"
    },
    {
      "A": "Упаковать",
      "B": "pack"
    },
    {
      "A": "Без сдачи",
      "B": "inget datum"
    },
    {
      "A": "Чаевые",
      "B": "tips"
    },
    {
      "A": "Вода",
      "B": "vatten"
    },
    {
      "A": "Свежий выжатый сок",
      "B": "färskt trängs saft"
    },
    {
      "A": "Сахар",
      "B": "socker"
    },
    {
      "A": "соль",
      "B": "salt"
    },
    {
      "A": "Молоко",
      "B": "mjölk"
    },
    {
      "A": "Рыба",
      "B": "fisk"
    },
    {
      "A": "Мясо",
      "B": "kött"
    },
    {
      "A": "Курица",
      "B": "kyckling"
    },
    {
      "A": "Баранина",
      "B": "fårkött"
    },
    {
      "A": "Говядина",
      "B": "nötkött"
    },
    {
      "A": "Перец",
      "B": "peppar"
    },
    {
      "A": "приправы",
      "B": "krydda"
    },
    {
      "A": "Картофель",
      "B": "potatis"
    },
    {
      "A": "Рис",
      "B": "ris"
    },
    {
      "A": "Чечевица",
      "B": "lins"
    },
    {
      "A": "Лук",
      "B": "lök"
    },
    {
      "A": "Чеснок",
      "B": "vitlök"
    },
    {
      "A": "Сладости",
      "B": "hopkok"
    },
    {
      "A": "Фрукты",
      "B": "frukt"
    },
    {
      "A": "Яблоки",
      "B": "äpplen"
    },
    {
      "A": "Виноград",
      "B": "druvor"
    },
    {
      "A": "Клубника",
      "B": "jordgubbe"
    },
    {
      "A": "Апельсины",
      "B": "apelsiner"
    },
    {
      "A": "Мандарина",
      "B": "mandarin"
    },
    {
      "A": "Лимон",
      "B": "citron"
    },
    {
      "A": "Гранат",
      "B": "granat"
    },
    {
      "A": "Бананы",
      "B": "bananer"
    },
    {
      "A": "Персики",
      "B": "persikor"
    },
    {
      "A": "Абрикос",
      "B": "aprikos"
    },
    {
      "A": "Манго",
      "B": "mango"
    },
    {
      "A": "Открыто",
      "B": "öppen"
    },
    {
      "A": "Закрыто",
      "B": "stängd"
    },
    {
      "A": "Скидка",
      "B": "rabatt"
    },
    {
      "A": "Очень дорого",
      "B": "mycket dyr"
    },
    {
      "A": "Дешево",
      "B": "billigt"
    },
    {
      "A": "Автобус",
      "B": "buss"
    },
    {
      "A": "троллейбус",
      "B": "trådbuss"
    },
    {
      "A": "Машина",
      "B": "bil"
    },
    {
      "A": "Такси",
      "B": "taxi"
    },
    {
      "A": "Стоянка",
      "B": "parkering"
    },
    {
      "A": "Автосервис",
      "B": "service"
    },
    {
      "A": "Остановка",
      "B": "stopp"
    },
    {
      "A": "Пожалуйста остановку",
      "B": "sluta"
    },
    {
      "A": "Сколько стоит проезд",
      "B": "hur mycket resor"
    },
    {
      "A": "Какая остановка?",
      "B": "sluta med det?"
    },
    {
      "A": "Мне скоро выходить",
      "B": "jag kommer snart att gå"
    },
    {
      "A": "Отправление",
      "B": "avresa"
    },
    {
      "A": "Поезд",
      "B": "tåg"
    },
    {
      "A": "Самолет",
      "B": "plan"
    },
    {
      "A": "Аэропорт",
      "B": "flygplats"
    },
    {
      "A": "Пожарная служба",
      "B": "brandkår"
    },
    {
      "A": "Полиция",
      "B": "polisen"
    },
    {
      "A": "Пожар",
      "B": "eld"
    },
    {
      "A": "Драка",
      "B": "dust"
    },
    {
      "A": "Скорая помощь",
      "B": "ambulans"
    },
    {
      "A": "Больница",
      "B": "sjukhus"
    },
    {
      "A": "У меня…",
      "B": "jag har ..."
    },
    {
      "A": "Ушиб",
      "B": "kontusion"
    },
    {
      "A": "Растяжение",
      "B": "styrka"
    },
    {
      "A": "Запасной выход",
      "B": "nödutgång"
    },
    {
      "A": "Аварийный выход",
      "B": "nödutgång"
    },
    {
      "A": "Аптека",
      "B": "apotek"
    },
    {
      "A": "Доктор",
      "B": "läkare"
    },
    {
      "A": "Официант",
      "B": "servitör"
    },
    {
      "A": "У вас есть свободные столики",
      "B": "du har fri tabeller"
    },
    {
      "A": "Я хочу заказать столик",
      "B": "jag vill boka ett bord"
    },
    {
      "A": "Чек пожалуйста",
      "B": "kontrollera"
    },
    {
      "A": "счет",
      "B": "konto"
    },
    {
      "A": "Примите мой заказ",
      "B": "var vänlig ta emot min beställning"
    },
    {
      "A": "Какого года вино",
      "B": "ar vin"
    },
    {
      "A": "Ваше фирменное блюда",
      "B": "din specialitet i hus"
    },
    {
      "A": "Чай",
      "B": "te"
    },
    {
      "A": "кофе",
      "B": "kaffe"
    },
    {
      "A": "Растворимый кофе",
      "B": "snabbkaffe"
    },
    {
      "A": "Суп",
      "B": "soppa"
    },
    {
      "A": "Оливки",
      "B": "oliv"
    },
    {
      "A": "Салат",
      "B": "sallad"
    },
    {
      "A": "Приготовленный на гриле",
      "B": "grillad"
    },
    {
      "A": "Жареный",
      "B": "rosta"
    },
    {
      "A": "Вареный",
      "B": "kokt"
    },
    {
      "A": "Я не ем мясо!",
      "B": "jag äter inte kött!"
    },
    {
      "A": "Вермишель",
      "B": "spån"
    },
    {
      "A": "Макароны",
      "B": "pasta"
    },
    {
      "A": "Фаршированный перец",
      "B": "fyllda paprikor"
    },
    {
      "A": "Сандвич",
      "B": "smörgås"
    },
    {
      "A": "Сыр",
      "B": "ost"
    },
    {
      "A": "сметана",
      "B": "gräddfil"
    },
    {
      "A": "кислая",
      "B": "sur"
    },
    {
      "A": "Пиво",
      "B": "öl"
    },
    {
      "A": "Вино",
      "B": "vin"
    }
  ]
}
